cognautic/__init__.py
cognautic/ai_engine.py
cognautic/auto_continuation.py
cognautic/cli.py
cognautic/codebase_indexer.py
cognautic/config.py
cognautic/confirmation.py
cognautic/file_tagger.py
cognautic/mcp_client.py
cognautic/mcp_commands.py
cognautic/mcp_config.py
cognautic/mcp_server.py
cognautic/memory.py
cognautic/multi_agent.py
cognautic/plugin_manager.py
cognautic/provider_endpoints.py
cognautic/repo_documenter.py
cognautic/rules.py
cognautic/utils.py
cognautic/voice_input.py
cognautic/websocket_server.py
cognautic/tools/__init__.py
cognautic/tools/ask_question.py
cognautic/tools/base.py
cognautic/tools/code_analysis.py
cognautic/tools/code_navigation.py
cognautic/tools/codebase_search.py
cognautic/tools/command_runner.py
cognautic/tools/directory_context.py
cognautic/tools/file_operations.py
cognautic/tools/file_reader.py
cognautic/tools/mcp_wrapper.py
cognautic/tools/registry.py
cognautic/tools/response_control.py
cognautic/tools/web_search.py
cognautic_cli-1.2.4.post1.dist-info/licenses/LICENSE
cognautic_cli-1.2.4.post1.dist-info/METADATA
cognautic_cli-1.2.4.post1.dist-info/WHEEL
cognautic_cli-1.2.4.post1.dist-info/entry_points.txt
cognautic_cli-1.2.4.post1.dist-info/top_level.txt
cognautic_cli-1.2.4.post1.dist-info/RECORD
