Metadata-Version: 2.4
Name: cognautic-cli
Version: 1.2.4.post1
Summary: A Python-based CLI AI coding agent that provides agentic development capabilities with multi-provider AI support and real-time interaction
Home-page: https://github.com/cognautic/cognautic-cli
Author: Cognautic
Author-email: Cognautic <cognautic@gmail.com>
Maintainer-email: Cognautic <cognautic@gmail.com>
License-Expression: MIT
Project-URL: Homepage, https://github.com/cognautic/cli
Project-URL: Documentation, https://cognautic.vercel.app/cognautic-cli.html
Project-URL: Repository, https://github.com/cognautic/cli.git
Project-URL: Issues, https://github.com/cognautic/cli/issues
Project-URL: Changelog, https://github.com/cognautic/cli/blob/main/CHANGELOG.md
Keywords: ai,cli,coding,assistant,development,automation
Classifier: Development Status :: 4 - Beta
Classifier: Intended Audience :: Developers
Classifier: Operating System :: OS Independent
Classifier: Programming Language :: Python :: 3
Classifier: Programming Language :: Python :: 3.8
Classifier: Programming Language :: Python :: 3.9
Classifier: Programming Language :: Python :: 3.10
Classifier: Programming Language :: Python :: 3.11
Classifier: Programming Language :: Python :: 3.12
Classifier: Topic :: Software Development :: Libraries :: Python Modules
Classifier: Topic :: Software Development :: Code Generators
Classifier: Topic :: Scientific/Engineering :: Artificial Intelligence
Requires-Python: >=3.8
License-File: LICENSE
Requires-Dist: click>=8.0.0
Requires-Dist: websockets>=10.0
Requires-Dist: aiohttp>=3.8.0
Requires-Dist: pydantic>=2.0.0
Requires-Dist: rich>=13.0.0
Requires-Dist: requests>=2.28.0
Requires-Dist: beautifulsoup4>=4.11.0
Requires-Dist: psutil>=5.9.0
Requires-Dist: cryptography>=3.4.0
Requires-Dist: keyring>=23.0.0
Requires-Dist: openai>=1.0.0
Requires-Dist: anthropic>=0.7.0
Requires-Dist: google-genai>=0.1.0
Requires-Dist: together>=0.2.0
Requires-Dist: nest-asyncio>=1.5.0
Requires-Dist: prompt-toolkit>=3.0.0
Requires-Dist: mcp>=0.1.0
Provides-Extra: tools
Requires-Dist: gitpython>=3.1.0; extra == "tools"
Requires-Dist: pyyaml>=6.0; extra == "tools"
Provides-Extra: voice
Requires-Dist: SpeechRecognition>=3.10.0; extra == "voice"
Requires-Dist: PyAudio>=0.2.14; extra == "voice"
Provides-Extra: dev
Requires-Dist: pytest>=7.0.0; extra == "dev"
Requires-Dist: pytest-asyncio>=0.21.0; extra == "dev"
Requires-Dist: black>=22.0.0; extra == "dev"
Requires-Dist: flake8>=5.0.0; extra == "dev"
Requires-Dist: mypy>=1.0.0; extra == "dev"
Requires-Dist: coverage>=6.0.0; extra == "dev"
Provides-Extra: all
Requires-Dist: cognautic-cli[dev,tools,voice]; extra == "all"
Dynamic: author
Dynamic: home-page
Dynamic: license-file
Dynamic: requires-python
